{
  "book_id": "PSA",
  "book_name": "Psalms",
  "chapter": 110,
  "verses": [
    {
      "texts": [
        "The Lord says to my Lord:",
        "\"Sit at my right hand,",
        "until I make your enemies your footstool.\""
      ],
      "verse": 1
    },
    {
      "texts": [
        "The Lord sends forth from Zion",
        "your mighty scepter.",
        "Rule in the midst of your enemies!"
      ],
      "verse": 2
    },
    {
      "texts": [
        "Your people will offer themselves freely",
        "on the day of your power,",
        "in holy garments;",
        "from the womb of the morning,",
        "the dew of your youth will be yours."
      ],
      "verse": 3
    },
    {
      "texts": [
        "The Lord has sworn",
        "and will not change his mind,",
        "\"You are a priest forever",
        "after the order of Melchizedek.\""
      ],
      "verse": 4
    },
    {
      "texts": [
        "The Lord is at your right hand;",
        "he will shatter kings on the day of his wrath."
      ],
      "verse": 5
    },
    {
      "texts": [
        "He will execute judgment among the nations,",
        "filling them with corpses;",
        "he will shatter chiefs",
        "over the wide earth."
      ],
      "verse": 6
    },
    {
      "texts": [
        "He will drink from the brook by the way;",
        "therefore he will lift up his head."
      ],
      "verse": 7
    }
  ]
}