{
  "book_id": "JOB",
  "book_name": "Job",
  "chapter": 12,
  "verses": [
    {
      "texts": [
        "And Job answered and said,",
        ""
      ],
      "verse": 1
    },
    {
      "texts": [
        "No doubt but ye are the people, and wisdom shall die with you.",
        ""
      ],
      "verse": 2
    },
    {
      "texts": [
        "But I have understanding as well as you; I am not inferior to you: yea, who knoweth not such things as these?",
        ""
      ],
      "verse": 3
    },
    {
      "texts": [
        "I am as one mocked of his neighbour, who calleth upon God, and he answereth him: the just upright man is laughed to scorn.",
        ""
      ],
      "verse": 4
    },
    {
      "texts": [
        "He that is ready to slip with his feet is as a lamp despised in the thought of him that is at ease.",
        ""
      ],
      "verse": 5
    },
    {
      "texts": [
        "The tabernacles of robbers prosper, and they that provoke God are secure; into whose hand God bringeth abundantly.",
        ""
      ],
      "verse": 6
    },
    {
      "texts": [
        "But ask now the beasts, and they shall teach thee; and the fowls of the air, and they shall tell thee:",
        ""
      ],
      "verse": 7
    },
    {
      "texts": [
        "Or speak to the earth, and it shall teach thee: and the fishes of the sea shall declare unto thee.",
        ""
      ],
      "verse": 8
    },
    {
      "texts": [
        "Who knoweth not in all these that the hand of the Lord hath wrought this?",
        ""
      ],
      "verse": 9
    },
    {
      "texts": [
        "In whose hand is the soul of every living thing, and the breath of all mankind.",
        ""
      ],
      "verse": 10
    },
    {
      "texts": [
        "Doth not the ear try words? and the mouth taste his meat?",
        ""
      ],
      "verse": 11
    },
    {
      "texts": [
        "With the ancient is wisdom; and in length of days understanding.",
        ""
      ],
      "verse": 12
    },
    {
      "texts": [
        "With him is wisdom and strength, he hath counsel and understanding.",
        ""
      ],
      "verse": 13
    },
    {
      "texts": [
        "Behold, he breaketh down, and it cannot be built again: he shutteth up a man, and there can be no opening.",
        ""
      ],
      "verse": 14
    },
    {
      "texts": [
        "Behold, he withholdeth the waters, and they dry up: also he sendeth them out, and they overturn the earth.",
        ""
      ],
      "verse": 15
    },
    {
      "texts": [
        "With him is strength and wisdom: the deceived and the deceiver are his.",
        ""
      ],
      "verse": 16
    },
    {
      "texts": [
        "He leadeth counsellors away spoiled, and maketh the judges fools.",
        ""
      ],
      "verse": 17
    },
    {
      "texts": [
        "He looseth the bond of kings, and girdeth their loins with a girdle.",
        ""
      ],
      "verse": 18
    },
    {
      "texts": [
        "He leadeth princes away spoiled, and overthroweth the mighty.",
        ""
      ],
      "verse": 19
    },
    {
      "texts": [
        "He removeth away the speech of the trusty, and taketh away the understanding of the aged.",
        ""
      ],
      "verse": 20
    },
    {
      "texts": [
        "He poureth contempt upon princes, and weakeneth the strength of the mighty.",
        ""
      ],
      "verse": 21
    },
    {
      "texts": [
        "He discovereth deep things out of darkness, and bringeth out to light the shadow of death.",
        ""
      ],
      "verse": 22
    },
    {
      "texts": [
        "He increaseth the nations, and destroyeth them: he enlargeth the nations, and straiteneth them again.",
        ""
      ],
      "verse": 23
    },
    {
      "texts": [
        "He taketh away the heart of the chief of the people of the earth, and causeth them to wander in a wilderness where there is no way.",
        ""
      ],
      "verse": 24
    },
    {
      "texts": [
        "They grope in the dark without light, and he maketh them to stagger like a drunken man."
      ],
      "verse": 25
    }
  ]
}